scripter/__init__.py
scripter/anchor.py
pythonista_scripter-2020.11.16.dist-info/WHEEL
pythonista_scripter-2020.11.16.dist-info/METADATA
pythonista_scripter-2020.11.16.dist-info/RECORD
