Metadata-Version: 2.1
Name: pythonista-scripter
Version: 2020.11.16
Summary: iOS Pythonista app UI and Scene animations and UI constraints
Home-page: https://github.com/mikaelho/scripter
License: TheUnlicense
Author: Mikael Honkala
Author-email: mikael.honkala@gmail.com
Classifier: Operating System :: iOS
